README.txt
setup.py
collective/__init__.py
collective.collage.maps.egg-info/PKG-INFO
collective.collage.maps.egg-info/SOURCES.txt
collective.collage.maps.egg-info/dependency_links.txt
collective.collage.maps.egg-info/entry_points.txt
collective.collage.maps.egg-info/namespace_packages.txt
collective.collage.maps.egg-info/not-zip-safe
collective.collage.maps.egg-info/requires.txt
collective.collage.maps.egg-info/top_level.txt
collective/collage/__init__.py
collective/collage/maps/__init__.py
collective/collage/maps/configure.zcml
collective/collage/maps/map.pt
collective/collage/maps/views.py
collective/collage/maps/patches/__init__.py
collective/collage/maps/patches/map.py
docs/HISTORY.txt