Metadata-Version: 1.0
Name: collective.collage.maps
Version: 1.2.1
Summary: Show Map view of a Plone folder in a Collage
Home-page: http://plone.org/products/collective.collage.maps
Author: Kees Hink
Author-email: hink@gw20e.com
License: GPL
Platform: UNKNOWN
Classifier: Programming Language :: Python
